jmespath-stubs/METADATA.toml
jmespath-stubs/__init__.pyi
jmespath-stubs/ast.pyi
jmespath-stubs/compat.pyi
jmespath-stubs/exceptions.pyi
jmespath-stubs/functions.pyi
jmespath-stubs/lexer.pyi
jmespath-stubs/parser.pyi
jmespath-stubs/py.typed
jmespath-stubs/visitor.pyi
types_jmespath-1.0.2.20250711.dist-info/licenses/LICENSE
types_jmespath-1.0.2.20250711.dist-info/METADATA
types_jmespath-1.0.2.20250711.dist-info/WHEEL
types_jmespath-1.0.2.20250711.dist-info/top_level.txt
types_jmespath-1.0.2.20250711.dist-info/RECORD
